gitbib/__init__.py
gitbib/abbreviations.json
gitbib/bibparse.py
gitbib/cache.py
gitbib/command_line.py
gitbib/gitbib.py
gitbib/query.py
gitbib/templates/index.html
gitbib/templates/template.bib
gitbib/templates/template.html
gitbib/templates/template.md
gitbib/templates/template.tex
gitbib-8.dist-info/entry_points.txt
gitbib-8.dist-info/WHEEL
gitbib-8.dist-info/METADATA
gitbib-8.dist-info/RECORD
