Metadata-Version: 1.2
Name: gitbib
Version: 8
Summary: Manage references with git.
Home-page: https://github.com/mpharrigan/gibib
License: UNKNOWN
Author: Matthew Harrigan
Author-email: matthew.harrigan@outlook.com
